MANIFEST.in
README.md
setup.py
humilis_asg/__init__.py
humilis_asg/mappings.yaml.j2
humilis_asg/meta.yaml.j2
humilis_asg/outputs.yaml.j2
humilis_asg/plugin.py
humilis_asg/resources.yaml.j2
humilis_asg.egg-info/PKG-INFO
humilis_asg.egg-info/SOURCES.txt
humilis_asg.egg-info/dependency_links.txt
humilis_asg.egg-info/entry_points.txt
humilis_asg.egg-info/not-zip-safe
humilis_asg.egg-info/requires.txt
humilis_asg.egg-info/top_level.txt