Metadata-Version: 1.1
Name: humilis-asg
Version: 0.4.1
Summary: Humilis plug-in to deploy an Autoscaling Group
Home-page: https://github.com/humilis/humilis-asg
Author: German Gomez-Herrero, FindHotel BV
Author-email: german@findhotel.net
License: MIT
Platform: UNKNOWN
Classifier: Programming Language :: Python :: 3
